ox_engine/__init__.py
ox_engine/do.py
ox_engine/log.py
ox_engine-0.0.99.dist-info/LICENSE
ox_engine-0.0.99.dist-info/METADATA
ox_engine-0.0.99.dist-info/WHEEL
ox_engine-0.0.99.dist-info/top_level.txt
ox_engine-0.0.99.dist-info/RECORD
