Metadata-Version: 2.1
Name: ox-engine
Version: 0.0.99
Summary: prompt data processer engine
Home-page: https://github.com/ox-ai/ox-engine.git
Author: Lokeshwaran M
Author-email: lokeshwaran.m23072003@gmail.com
License: MIT
Keywords: ox-engine ox-ai
License-File: LICENSE
Requires-Dist: setuptools ==68.1.2
